vi_nlp_core/__init__.py
vi_nlp_core/build_name_dict.py
vi_nlp_core/tester.py
vi_nlp_core/data/dictionary_normalize_date.json
vi_nlp_core/data/stopwords.pkl
vi_nlp_core/data/symptoms.txt
vi_nlp_core/ner/__init__.py
vi_nlp_core/ner/date_matcher.py
vi_nlp_core/ner/dep_matcher.py
vi_nlp_core/ner/extractor.py
vi_nlp_core/ner/gender_matcher.py
vi_nlp_core/ner/pername_matcher.py
vi_nlp_core/ner/symptom_matcher.py
vi_nlp_core/ner/time_matcher.py
vi_nlp_core/utils/__init__.py
vi_nlp_core/utils/date_pattern.py
vi_nlp_core/utils/dep_pattern.py
vi_nlp_core/utils/gender_pattern.py
vi_nlp_core/utils/pername_pattern.py
vi_nlp_core/utils/preproces.py
vi_nlp_core/utils/time_pattern.py
vi_nlp_core/utils/util.py
vi_nlp_core-1.1.12.dist-info/METADATA
vi_nlp_core-1.1.12.dist-info/WHEEL
vi_nlp_core-1.1.12.dist-info/top_level.txt
vi_nlp_core-1.1.12.dist-info/RECORD
