Metadata-Version: 2.1
Name: vi-nlp-core
Version: 1.1.12
Summary: vi-core-nlp is a library that supports Vietnamese NER by pattern matching .
Home-page: https://github.com/demdecuong/vi-core-nlp/tree/master
Author: minhnp et al.
Author-email: nguyenphucminh2804@gmail.com
License: UNKNOWN
Keywords: vi_nlp_core
Platform: UNKNOWN
Classifier: Programming Language :: Python :: 3
Requires-Python: >=3.6
Requires-Dist: vietnam-number (==1.0.3)
Requires-Dist: fuzzywuzzy (==0.18.0)
Requires-Dist: datetime (==4.3)
Requires-Dist: python-Levenshtein (==0.12.2)
